rbash/__init__.py
rbash/cli.py
rbash/rbash.sh
rbash/remote.py
remote_bash-2.0.0.dist-info/licenses/LICENSE
remote_bash-2.0.0.dist-info/METADATA
remote_bash-2.0.0.dist-info/WHEEL
remote_bash-2.0.0.dist-info/entry_points.txt
remote_bash-2.0.0.dist-info/top_level.txt
remote_bash-2.0.0.dist-info/RECORD
