Metadata-Version: 2.4
Name: remote_bash
Version: 2.0.0
Summary: Remote Bash Shell with reverse SSHFS local directory mounting
Author-email: Leo <leoustc@icloud.com>
Requires-Python: >=3.8
License-File: LICENSE
Dynamic: license-file
